{
  "preguntas": [
    {
      "descripcion": "¿En cuáles de éstos instrumentos has invertido alguna vez?",
      "TipoComponente": "CHECKBOX",
      "categoria": {
        "nombre": "Test Inversor"
      },  
      "seccion": {
        "nombre": "Tolerancia al riesgo"
      },
      "respuestas": [{
          "nombre": "Plazo Fijo",
          "valor": 0
        },
        {
          "nombre": "Fondos Comunes de Inversion (De renta fija)",
          "valor": 0
        },
        {
          "nombre": "Bonos",
          "valor": 1
        },
        {
          "nombre": "Acciones",
          "valor": 2
        },
        {
          "nombre": "Opciones",
          "valor": 3
        },
        {
          "nombre": "Futuros",
          "valor": 4
        }
      ]
    },
    {
      "descripcion": "¿Cuál es tu grado de conocimiento de cada instrumento?",
      "TipoComponente": "BOTON",
      "categoria": {
        "nombre": "Test Inversor"
      },
      "seccion": {
        "nombre": "Tolerancia al riesgo"
      },
      "respuestas": [{
          "instrumento": "Fondos Comunes de Inversión",
          "nombre": "BAJA",
          "valor": 0,
          "orden": 1
        },
        {
          "instrumento": "Fondos Comunes de Inversión",
          "nombre": "MEDIA",
          "valor": 0,
          "orden": 2
        },
        {
          "instrumento": "Fondos Comunes de Inversión",
          "nombre": "ALTA",
          "valor": 1,
          "orden": 3
        },
        {
          "instrumento": "Bonos",
          "nombre": "BAJA",
          "valor": 0,
          "orden": 1
        },
        {
          "instrumento": "Bonos",
          "nombre": "MEDIA",
          "valor": 0,
          "orden": 2
        },
        {
          "instrumento": "Bonos",
          "nombre": "ALTA",
          "valor": 1,
          "orden": 3
        },
        {
          "instrumento": "Acciones",
          "nombre": "BAJA",
          "valor": 0,
          "orden": 1
        },
        {
          "instrumento": "Acciones",
          "nombre": "MEDIA",
          "valor": 1,
          "orden": 2
        },
        {
          "instrumento": "Acciones",
          "nombre": "ALTA",
          "valor": 2,
          "orden": 3
        },
        {
          "instrumento": "Opciones",
          "nombre": "BAJA",
          "valor": 1,
          "orden": 1
        },
        {
          "instrumento": "Opciones",
          "nombre": "MEDIA",
          "valor": 2,
          "orden": 2
        },
        {
          "instrumento": "Opciones",
          "nombre": "ALTA",
          "valor": 3,
          "orden": 3
        },
        {
          "instrumento": "Futuros",
          "nombre": "BAJA",
          "valor": 1,
          "orden": 1
        },
        {
          "instrumento": "Futuros",
          "nombre": "MEDIA",
          "valor": 2,
          "orden": 2
        },
        {
          "instrumento": "Futuros",
          "nombre": "ALTA",
          "valor": 3,
          "orden": 3
        }
      ]
    },
    {
      "descripcion": "¿Cuál es el plazo máximo que estarías dispuesto a mantener tus inversiones?",
      "TipoComponente": "RADIO",
      "categoria": {
        "nombre": "Test Inversor"
      },
      "seccion": {
        "nombre": "Horizonte Temporal"
      },
      "respuestas": [{
          "nombre": "Menos de 3 años",
          "valor": 1
        },
        {
          "nombre": "Entre 3 y 5 años",
          "valor": 3
        },
        {
          "nombre": "Entre 6 y 10 años",
          "valor": 7
        },
        {
          "nombre": "Mas de 11 años",
          "valor": 10
        }
      ]
    },
    {
      "descripcion": "¿Cuántos años tenés?",
      "TipoComponente": "RADIO",
      "categoria": {
        "nombre": "Test Inversor"
      },
      "seccion": {
        "nombre": "Horizonte Temporal"
      },
      "respuestas": [{
          "nombre": "Más de 50",
          "valor": 0
        },
        {
          "nombre": "41 a 50",
          "valor": 1
        },
        {
          "nombre": "30 a 40",
          "valor": 4
        },
        {
          "nombre": "Menos de 30",
          "valor": 8
        }
      ]
    },
    {
      "descripcion": "Al momento de realizar una inversión, buscas:",
      "TipoComponente": "RADIO",
      "categoria": {
        "nombre": "Test Inversor"
      },
      "seccion": {
        "nombre": "Tolerancia al riesgo"
      },
      "respuestas": [{
          "nombre": "Cubrir tu capital de la inflación y/o devaluación buscando el menor riesgo posible.",
          "valor": 0
        },
        {
          "nombre": "Obtener un rendimiento superior a la inflación y/o devaluación aceptando arriesgar tu capital.",
          "valor": 6
        },
        {
          "nombre": "Lograr un rendimiento considerablemente superior a la inflación y/o devaluación aceptando posibles pérdidas de capital",
          "valor": 10
        }
      ]
    },
    {
      "descripcion": "Dirías que tu actual capacidad de ahorro es de:",
      "TipoComponente": "RADIO",
      "categoria": {
        "nombre": "Test Inversor"
      },
      "seccion": {
        "nombre": "Tolerancia al riesgo"
      },
      "respuestas": [{
          "nombre": "Menos de 2.000 Dólares al año.",
          "valor": 0
        },
        {
          "nombre": "Entre 2.000 Dólares y 6.000 Dólares al año.",
          "valor": 6
        },
        {
          "nombre": "Más de 6.000 Dólares al año.",
          "valor": 10
        }
      ]
    }
  ]
}
